flask_hooker
