Metadata-Version: 1.1
Name: Flask-Hooker
Version: 1.0.2
Summary: Receive and manage webhooks of several services at the same time
Home-page: http://github.com/doblel/Flask-Hooker/
Author: Lisandro Lucatti (doblel)
Author-email: lucattilisandro@gmail.com
License: MIT
Platform: any
Classifier: Environment :: Web Environment
Classifier: Intended Audience :: Developers
Classifier: License :: OSI Approved :: MIT License
Classifier: Operating System :: OS Independent
Classifier: Programming Language :: Python
Classifier: Programming Language :: Python :: 2
Classifier: Programming Language :: Python :: 3
Classifier: Topic :: Internet :: WWW/HTTP :: Dynamic Content
Classifier: Topic :: Software Development :: Libraries :: Python Modules
